[
  {
    "race_ref_method_nm": "Air",
    "race_ref_to": "444",
    "sort_ord": null,
    "pjt_sq": "129",
    "race_ref_trayedm_no": "121444",
    "race_ref_len": "213",
    "race_ref_seq": "0001114",
    "race_ref_rem": "234",
    "race_ref_method": "A",
    "race_ref_temp": "23",
    "race_ref_from": "121"
  },
  {
    "race_ref_method_nm": "Air",
    "race_ref_to": "556",
    "sort_ord": null,
    "pjt_sq": "129",
    "race_ref_trayedm_no": "121556",
    "race_ref_len": "345",
    "race_ref_seq": "0001116",
    "race_ref_rem": "456",
    "race_ref_method": "A",
    "race_ref_temp": "34",
    "race_ref_from": "121"
  },
  {
    "race_ref_method_nm": "Air",
    "race_ref_to": "fwef",
    "sort_ord": null,
    "pjt_sq": "129",
    "race_ref_trayedm_no": "121fwef",
    "race_ref_len": "2312",
    "race_ref_seq": "0001119",
    "race_ref_rem": "324",
    "race_ref_method": "A",
    "race_ref_temp": "23",
    "race_ref_from": "121"
  },
  {
    "race_ref_method_nm": "Air",
    "race_ref_to": "123",
    "sort_ord": null,
    "pjt_sq": "129",
    "race_ref_trayedm_no": "444123",
    "race_ref_len": "234",
    "race_ref_seq": "0001115",
    "race_ref_rem": "345",
    "race_ref_method": "A",
    "race_ref_temp": "45",
    "race_ref_from": "444"
  },
  {
    "race_ref_method_nm": "Air",
    "race_ref_to": "43",
    "sort_ord": null,
    "pjt_sq": "129",
    "race_ref_trayedm_no": "554543",
    "race_ref_len": "456",
    "race_ref_seq": "0001118",
    "race_ref_rem": "456",
    "race_ref_method": "A",
    "race_ref_temp": "45",
    "race_ref_from": "5545"
  },
  {
    "race_ref_method_nm": "Air",
    "race_ref_to": "5545",
    "sort_ord": null,
    "pjt_sq": "129",
    "race_ref_trayedm_no": "5565545",
    "race_ref_len": "456",
    "race_ref_seq": "0001117",
    "race_ref_rem": "456",
    "race_ref_method": "A",
    "race_ref_temp": "546",
    "race_ref_from": "556"
  },
  {
    "race_ref_method_nm": "Air",
    "race_ref_to": "FF",
    "sort_ord": null,
    "pjt_sq": "129",
    "race_ref_trayedm_no": "A1FF",
    "race_ref_len": "213",
    "race_ref_seq": "0001111",
    "race_ref_rem": "231",
    "race_ref_method": "A",
    "race_ref_temp": "2",
    "race_ref_from": "A1"
  },
  {
    "race_ref_method_nm": "Underground",
    "race_ref_to": "DD",
    "sort_ord": null,
    "pjt_sq": "129",
    "race_ref_trayedm_no": "AADD",
    "race_ref_len": "4",
    "race_ref_seq": "0001108",
    "race_ref_rem": "123",
    "race_ref_method": "U",
    "race_ref_temp": "12",
    "race_ref_from": "AA"
  },
  {
    "race_ref_method_nm": "Air",
    "race_ref_to": "ZZ",
    "sort_ord": null,
    "pjt_sq": "129",
    "race_ref_trayedm_no": "CCZZ",
    "race_ref_len": "123",
    "race_ref_seq": "0001110",
    "race_ref_rem": "123",
    "race_ref_method": "A",
    "race_ref_temp": "12",
    "race_ref_from": "CC"
  },
  {
    "race_ref_method_nm": "Air",
    "race_ref_to": "CC",
    "sort_ord": null,
    "pjt_sq": "129",
    "race_ref_trayedm_no": "DDCC",
    "race_ref_len": "123",
    "race_ref_seq": "0001109",
    "race_ref_rem": "123",
    "race_ref_method": "A",
    "race_ref_temp": "12",
    "race_ref_from": "DD"
  },
  {
    "race_ref_method_nm": "Air",
    "race_ref_to": "TT",
    "sort_ord": null,
    "pjt_sq": "129",
    "race_ref_trayedm_no": "FFTT",
    "race_ref_len": "23",
    "race_ref_seq": "0001112",
    "race_ref_rem": "23",
    "race_ref_method": "A",
    "race_ref_temp": "45",
    "race_ref_from": "FF"
  },
  {
    "race_ref_method_nm": "Air",
    "race_ref_to": "Z1",
    "sort_ord": null,
    "pjt_sq": "129",
    "race_ref_trayedm_no": "TTZ1",
    "race_ref_len": "1",
    "race_ref_seq": "0001113",
    "race_ref_rem": "34",
    "race_ref_method": "A",
    "race_ref_temp": "23",
    "race_ref_from": "TT"
  },
  {
    "race_ref_method_nm": "Air",
    "race_ref_to": "5545",
    "sort_ord": null,
    "pjt_sq": "129",
    "race_ref_trayedm_no": "fwef5545",
    "race_ref_len": "321",
    "race_ref_seq": "0001120",
    "race_ref_rem": "243",
    "race_ref_method": "A",
    "race_ref_temp": "23",
    "race_ref_from": "fwef"
  }
]